Metadata-Version: 2.1
Name: consoleAnsiInterface
Version: 1.1.0
Summary: Console interface with ANSI sequences for Windows
Author: szachy-a
